asmc/asmc/__init__.py
asmc/asmc/asmc_python_bindings.cpython-311-x86_64-linux-gnu.so
asmc_asmc.libs/libboost_iostreams-5e889418.so.1.66.0
asmc_asmc.libs/libboost_program_options-4ff2bf56.so.1.66.0
asmc_asmc.libs/libboost_regex-2b30dfd4.so.1.66.0
asmc_asmc.libs/libbz2-a1e77c99.so.1.0.6
asmc_asmc.libs/libicudata-05640f77.so.60.3
asmc_asmc.libs/libicui18n-4fcc01ea.so.60.3
asmc_asmc.libs/libicuuc-14201aad.so.60.3
asmc_asmc.libs/liblzma-51a76f52.so.5.2.4
include/module.modulemap
include/concepts/compare.hpp
include/concepts/concepts.hpp
include/concepts/swap.hpp
include/concepts/type_traits.hpp
include/eigen3/signature_of_eigen3_matrix_library
include/eigen3/Eigen/Cholesky
include/eigen3/Eigen/CholmodSupport
include/eigen3/Eigen/Core
include/eigen3/Eigen/Dense
include/eigen3/Eigen/Eigen
include/eigen3/Eigen/Eigenvalues
include/eigen3/Eigen/Geometry
include/eigen3/Eigen/Householder
include/eigen3/Eigen/IterativeLinearSolvers
include/eigen3/Eigen/Jacobi
include/eigen3/Eigen/KLUSupport
include/eigen3/Eigen/LU
include/eigen3/Eigen/MetisSupport
include/eigen3/Eigen/OrderingMethods
include/eigen3/Eigen/PaStiXSupport
include/eigen3/Eigen/PardisoSupport
include/eigen3/Eigen/QR
include/eigen3/Eigen/QtAlignedMalloc
include/eigen3/Eigen/SPQRSupport
include/eigen3/Eigen/SVD
include/eigen3/Eigen/Sparse
include/eigen3/Eigen/SparseCholesky
include/eigen3/Eigen/SparseCore
include/eigen3/Eigen/SparseLU
include/eigen3/Eigen/SparseQR
include/eigen3/Eigen/StdDeque
include/eigen3/Eigen/StdList
include/eigen3/Eigen/StdVector
include/eigen3/Eigen/SuperLUSupport
include/eigen3/Eigen/UmfPackSupport
include/eigen3/Eigen/src/Cholesky/LDLT.h
include/eigen3/Eigen/src/Cholesky/LLT.h
include/eigen3/Eigen/src/Cholesky/LLT_LAPACKE.h
include/eigen3/Eigen/src/CholmodSupport/CholmodSupport.h
include/eigen3/Eigen/src/Core/ArithmeticSequence.h
include/eigen3/Eigen/src/Core/Array.h
include/eigen3/Eigen/src/Core/ArrayBase.h
asmc_asmc-1.4.0.dist-info/METADATA
asmc_asmc-1.4.0.dist-info/WHEEL
asmc_asmc-1.4.0.dist-info/RECORD
asmc_asmc-1.4.0.dist-info/licenses/COPYING
asmc_asmc-1.4.0.dist-info/licenses/LICENSE
